deutschland/nina/__init__.py
deutschland/nina/api/__init__.py
deutschland/nina/api/default_api.py
deutschland/nina/api_client.py
deutschland/nina/apis/__init__.py
deutschland/nina/configuration.py
deutschland/nina/exceptions.py
deutschland/nina/model/__init__.py
deutschland/nina/model/ags_covid_rules.py
deutschland/nina/model/ags_covid_rules_common.py
deutschland/nina/model/ags_covid_rules_icon.py
deutschland/nina/model/ags_covid_rules_level.py
deutschland/nina/model/ags_covid_rules_regulations.py
deutschland/nina/model/ags_covid_rules_regulations_sections.py
deutschland/nina/model/ags_covid_rules_regulations_sections_bund.py
deutschland/nina/model/ags_covid_rules_regulations_sections_bund_icon.py
deutschland/nina/model/ags_covid_rules_regulations_sections_kreis.py
deutschland/nina/model/ags_covid_rules_regulations_sections_kreis_icon.py
deutschland/nina/model/ags_covid_rules_regulations_sections_land.py
deutschland/nina/model/ags_covid_rules_regulations_sections_land_icon.py
deutschland/nina/model/ags_covid_rules_rules.py
deutschland/nina/model/ags_overview_result.py
deutschland/nina/model/map_warnings.py
deutschland/nina/model_utils.py
deutschland/nina/models/__init__.py
deutschland/nina/rest.py
de_nina-1.0.2.dist-info/WHEEL
de_nina-1.0.2.dist-info/METADATA
de_nina-1.0.2.dist-info/RECORD
